[
    {
        "moto_id": "M47",
        "zona": "ZC2",
        "vaga": 16,
        "status": "entrada",
        "correct": true,
        "timestamp": 148685
    },
    {
        "moto_id": "M48",
        "zona": "ZE",
        "vaga": 14,
        "status": "entrada",
        "correct": false,
        "timestamp": 151739
    },
    {
        "moto_id": "M1",
        "zona": "ZE",
        "vaga": 15,
        "status": "entrada",
        "correct": false,
        "timestamp": 8102
    },
    {
        "moto_id": "M17",
        "zona": "ZC1",
        "vaga": 10,
        "status": "entrada",
        "correct": true,
        "timestamp": 63179
    },
    {
        "moto_id": "M18",
        "zona": "ZC2",
        "vaga": 18,
        "status": "entrada",
        "correct": true,
        "timestamp": 66248
    },
    {
        "moto_id": "M19",
        "zona": "ZC1",
        "vaga": 3,
        "status": "entrada",
        "correct": false,
        "timestamp": 69269
    },
    {
        "moto_id": "M20",
        "zona": "ZC1",
        "vaga": 11,
        "status": "entrada",
        "correct": true,
        "timestamp": 72364
    },
    {
        "moto_id": "M21",
        "zona": "ZE",
        "vaga": 16,
        "status": "entrada",
        "correct": true,
        "timestamp": 75779
    },
    {
        "moto_id": "M22",
        "zona": "ZC1",
        "vaga": 5,
        "status": "entrada",
        "correct": false,
        "timestamp": 79062
    },
    {
        "moto_id": "M23",
        "zona": "ZC1",
        "vaga": 10,
        "status": "entrada",
        "correct": true,
        "timestamp": 82152
    }
]